ugbio_srsnv/__init__.py
ugbio_srsnv/shap_plotting.py
ugbio_srsnv/srsnv_inference.py
ugbio_srsnv/srsnv_inference_utils.py
ugbio_srsnv/srsnv_plotting_utils.py
ugbio_srsnv/srsnv_report.py
ugbio_srsnv/srsnv_training.py
ugbio_srsnv/srsnv_training_legacy.py
ugbio_srsnv/srsnv_training_utils.py
ugbio_srsnv/srsnv_utils.py
ugbio_srsnv/toc_preprocessor.py
ugbio_srsnv/trinuc_histogram_plotting.py
ugbio_srsnv/reports/srsnv_report.ipynb
ugbio_srsnv-1.20.0.dist-info/METADATA
ugbio_srsnv-1.20.0.dist-info/WHEEL
ugbio_srsnv-1.20.0.dist-info/entry_points.txt
ugbio_srsnv-1.20.0.dist-info/top_level.txt
ugbio_srsnv-1.20.0.dist-info/RECORD
