Metadata-Version: 2.4
Name: ugbio_srsnv
Version: 1.20.0
Summary: Ultima Genomics SRSNV utils
Author-email: Itai Rusinek <itai.rusinek@ultimagen.com>, Gat Krieger <gat.krieger@ultimagen.com>, Inbal Zelig <inbal.zelig@ultimagen.com>, Ori Hirschberg <ori.hirschberg@ultimagen.com>, Rina Schwartz <rina.schwartz@ultimagen.com>, Doron Shem-Tov <doron.shemtov@ultimagen.com>, Avigail Moldovan <avigail.moldovan@ultimagen.com>
License: Apache-2.0
Requires-Python: >=3.11
Requires-Dist: ugbio_core[ml,reports,vcfbed]
Requires-Dist: ugbio_ppmseq
Requires-Dist: ugbio_featuremap
Requires-Dist: numba>=0.60.0
Requires-Dist: shap>=0.46.0
